{
  "version": "7",
  "dialect": "sqlite",
  "entries": [
    {
      "idx": 0,
      "version": "6",
      "when": 1738640354931,
      "tag": "0000_init",
      "breakpoints": true
    },
    {
      "idx": 1,
      "version": "6",
      "when": 1738738621650,
      "tag": "0001_init",
      "breakpoints": true
    },
    {
      "idx": 2,
      "version": "6",
      "when": 1738738832555,
      "tag": "0002_init",
      "breakpoints": true
    },
    {
      "idx": 3,
      "version": "6",
      "when": 1738738977098,
      "tag": "0003_init",
      "breakpoints": true
    }
  ]
}